frye/__init__.py
frye/frye.py
frye-0.0.2.dist-info/LICENSE
frye-0.0.2.dist-info/METADATA
frye-0.0.2.dist-info/WHEEL
frye-0.0.2.dist-info/top_level.txt
frye-0.0.2.dist-info/RECORD
